cbrzn_ethereum_provider_py/__init__.py
cbrzn_ethereum_provider_py/connection.py
cbrzn_ethereum_provider_py/connections.py
cbrzn_ethereum_provider_py/networks.py
cbrzn_ethereum_provider_py/wrap/types.py
cbrzn_ethereum_provider_py-0.0.2.dist-info/WHEEL
cbrzn_ethereum_provider_py-0.0.2.dist-info/METADATA
cbrzn_ethereum_provider_py-0.0.2.dist-info/RECORD
